{"name":"Github","slug":"Github","count":1,"postlist":[{"title":"GithubWebhook解析服务","uid":"cdcb5c6b90ae779df8934cdee5c82576","slug":"githubWebhook","date":"2023-10-26T15:18:13.000Z","updated":"2024-02-22T03:52:13.945Z","comments":true,"path":"api/articles/githubWebhook.json","keywords":"计算机技术,大数据,人工智能","cover":"https://images.unsplash.com/photo-1630514969818-94aefc42ec47?crop=entropy&cs=tinysrgb&fit=max&fm=jpg&ixid=M3wzNjAwOTd8MHwxfHNlYXJjaHw0fHxnaXRodWJ8ZW58MHx8fHwxNjk4MzMzNjcyfDA&ixlib=rb-4.0.3&q=80&w=1080","text":"WebhookWebhook是一种基于HTTP的回调函数，可在两个应用编程接口（API）之间实现轻量级的事件驱动通信。客户端向服务器API提供唯一URL，并指定...","link":"","photos":[],"count_time":{"symbolsCount":"16k","symbolsTime":"15 mins."},"categories":[{"name":"技术帖子","slug":"技术帖子","count":4,"path":"api/categories/技术帖子.json"}],"tags":[{"name":"Github","slug":"Github","count":1,"path":"api/tags/Github.json"},{"name":"Webhook","slug":"Webhook","count":1,"path":"api/tags/Webhook.json"}],"author":{"name":"以太工坊","slug":"blog-author","avatar":"/img/logo.png","link":"/","description":"分享我的课程学习笔记、经验与有趣的小玩意.图片等资源无法加载时请使用代理","socials":{"github":"https://github.com/Tim-Saijun","twitter":"","stackoverflow":"","wechat":"","qq":"","weibo":"","zhihu":"","csdn":"","juejin":"","customs":{"telegram":{"icon":"/img/telegram.svg","link":"https://t.me/tim_run"},"Email":{"icon":"/img/mail.svg","link":"mailto:b@zair.top"},"RSS":{"icon":"/img/rss.svg","link":"/atom.xml"}}}}}]}